LICENSE.txt
MANIFEST.in
README.rst
setup.py
frozenobj/__init__.py
frozenobj/proxy.py
frozenobj.egg-info/PKG-INFO
frozenobj.egg-info/SOURCES.txt
frozenobj.egg-info/dependency_links.txt
frozenobj.egg-info/not-zip-safe
frozenobj.egg-info/requires.txt
frozenobj.egg-info/top_level.txt